{
  "name": "Lactating Mothers Enrolment",
  "uuid": "96dae617-1b01-4de7-a783-627e2a78277c",
  "formType": "ProgramEnrolment",
  "formElementGroups": [
    {
      "uuid": "86576589-d6ea-4177-a750-93c518501296",
      "name": "Primary information",
      "display": "Primary information",
      "displayOrder": 1,
      "formElements": [
        {
          "name": "How often have you been pregnant",
          "uuid": "47116772-c13a-4794-844b-2b5fb01403c4",
          "keyValues": [],
          "concept": {
            "name": "Gravida",
            "uuid": "dc2c23e9-19ad-471f-81d1-213069ccc975"
          },
          "displayOrder": 1,
          "mandatory": true
        },
        {
          "name": "Number of alive children",
          "uuid": "ead4e9a9-f328-4c73-8583-43a96409ece7",
          "keyValues": [],
          "concept": {
            "name": "Number of alive children",
            "uuid": "85a2e410-411d-4243-bef9-d5d047bde636"
          },
          "displayOrder": 2,
          "mandatory": true
        },
        {
          "name": "If a child has died, tell the reason",
          "uuid": "67404d95-0f1d-4944-81b6-7566ae8eefb8",
          "keyValues": [],
          "concept": {
            "name": "If a child has died, tell the reason",
            "uuid": "f995ca8f-c075-4f87-a349-cf7d3cec79c3"
          },
          "displayOrder": 3,
          "mandatory": true
        },
        {
          "name": "Whether have mamta card",
          "uuid": "aff347c5-82ff-458f-901c-73ce2dd0ccc4",
          "keyValues": [],
          "type": "SingleSelect",
          "concept": {
            "name": "Whether have mamta card",
            "uuid": "3299cda4-3c1a-4dd7-8a69-5d756136a5cd"
          },
          "displayOrder": 4,
          "mandatory": true
        },
        {
          "name": "Reason for not having mamta card",
          "uuid": "5614f7a8-8497-42ca-aeb2-d191abd30275",
          "keyValues": [],
          "type": "MultiSelect",
          "concept": {
            "name": "Reason for not having mamta card",
            "uuid": "b94c9eba-9c44-4262-a870-56b0257cc115"
          },
          "displayOrder": 5,
          "mandatory": true
        },
        {
          "name": "Other reason for not having mamta card",
          "uuid": "ae3ec169-6975-4e6b-b296-b3e6822f5868",
          "keyValues": [],
          "concept": {
            "uuid": "b2789df2-9751-435a-974b-02f50d30f450",
            "name": "Other reason for not having mamta card"
          },
          "displayOrder": 6,
          "mandatory": true
        },
        {
          "name": "Place of delivery",
          "uuid": "cb256fdb-e513-4916-96cb-166528f60ed3",
          "keyValues": [],
          "type": "SingleSelect",
          "concept": {
            "uuid": "a0405799-1e3c-40ef-90ba-84c9c0931660"
          },
          "displayOrder": 7,
          "mandatory": true
        },        
        {
          "name": "Type of delivery",
          "uuid": "8bb92c3d-2a3d-4da1-ad07-fc358664c3d2",
          "keyValues": [],
          "type": "SingleSelect",
          "concept": {
            "name": "Type of delivery",
            "uuid": "69d0acf1-c32b-4694-9bc2-874b5e7a44c8"
          },
          "displayOrder": 8,
          "mandatory": true
        },

        {
          "name": "Age of youngest child",
          "uuid": "77824550-9703-441c-b6f3-9bcba1078ff8",
          "keyValues": [
            {
              "key": "durationOptions",
              "value": [
                "months"
              ]
            }
          ],
          "concept": {
            "name": "Age of youngest child",
            "uuid": "305f693c-c8b6-4e3e-9a82-a6e91a3e462f"
          },
          "displayOrder": 9,
          "mandatory": true
        }
      ]
    },
    {
      "uuid": "023295dc-fafa-4db1-a3f8-2dcfbf8de86b",
      "name": "Information about knowledge on breastfeeding and complementary food",
      "display": "Information about knowledge on breastfeeding and complementary food",
      "displayOrder": 2,
      "formElements": [
        {
          "name": "What should be given to the child soon after birth",
          "uuid": "5a5f5d27-a815-408d-8526-f4cf72b67dcd",
          "type": "SingleSelect",
          "keyValues": [],
          "concept": {
            "name": "What should be given to the child soon after birth",
            "uuid": "cdb77995-68f1-4d61-877e-dcb4bf46cdad"
          },
          "displayOrder":1,
          "mandatory": true
        },
        {
          "name": "For how long child should be breast fed exclusively",
          "uuid": "74ed759c-b759-428f-b264-7f8889c09a1b",
          "type": "SingleSelect",
          "keyValues": [],
          "concept": {
            "name": "For how long child should be breast fed exclusively",
            "uuid": "48cc9d87-5009-4539-b9f7-f910240d23ce"
          },
          "displayOrder":2,
          "mandatory": true
        },
        {
          "name": "How often child should be breastfed in a day",
          "uuid": "a6fb6c03-e6f9-494f-a925-7dcd3e2b60ab",
          "keyValues": [],
          "type": "SingleSelect",
          "concept": {
            "name": "How often child should be breastfed in a day",
            "uuid": "fc6632c3-1cd7-463d-af28-fba15a9aab67"
          },
          "displayOrder": 3,
          "mandatory": true
        },
        {
          "name": "Should child be breastfed on demand",
          "uuid": "1eb57df7-a23b-429b-ba74-168b28edee3e",
          "type": "SingleSelect",
          "concept": {
            "name": "Should child be breastfed on demand",
            "uuid": "99296030-ffc3-46dd-92cf-e2de907f93bc"
          },
          "displayOrder": 4,
          "mandatory": true
        },
        {
          "name": "Should child be breastfed on certain time",
          "uuid": "98d78f25-b2f4-4931-80ea-82e0929e8459",
          "type": "SingleSelect",
          "concept": {
            "name": "Should child be breastfed on certain time",
            "uuid": "a8b1b330-a3ca-431b-9dac-5ffa8c247418"
          },
          "displayOrder": 5,
          "mandatory": true
        },
        {
          "name": "At what age child should be given water",
          "uuid": "041a25a8-18cb-4bee-9d21-b19927c118b6",
          "type": "SingleSelect",
          "keyValues": [],
          "concept": {
            "name": "At what age child should be given water",
            "uuid": "b806f1ac-aa9b-45b9-917b-6fc050afd9cc"
          },
          "displayOrder":6,
          "mandatory": true
        },
        {
          "name": "At what age child should be given complementary food",
          "uuid": "505f1c7f-2bf3-497e-891c-d47f0efa5429",
          "type": "SingleSelect",
          "keyValues": [],
          "concept": {
            "name": "At what age child should be given complementary food",
            "uuid": "f8954994-e228-48b8-aa01-70c45ab41046"
          },
          "displayOrder":7,
          "mandatory": true
        },
        {
          "name": "What types of complementary food should be given to the child",
          "uuid": "c0298631-a3ae-4345-9be5-6670bf63d824",
          "keyValues": [],
          "concept": {
            "name": "What types of complementary food should be given to the child",
            "uuid": "6d5a9fdc-4e64-452a-92f1-20c9fdca5f1f"
          },
          "displayOrder":7.1,
          "mandatory": true
        },
        {
          "name": "Other types of complementary food that should be given to the child",
          "uuid": "366255f2-2325-46dd-9b9f-e901e9473977",
          "keyValues": [],
          "concept": {
            "uuid": "ac7fc74a-1b1e-43fe-a93f-39b175a59c2c",
            "name": "Other types of complementary food that should be given to the child"
          },
          "displayOrder":7.2,
          "mandatory": false
        },
        {
          "name": "What should be kept in mind when preparing a food for child",
          "uuid": "1ba1e5b3-fd18-4720-b944-652fabd190a2",
          "type": "MultiSelect",
          "keyValues": [],
          "concept": {
            "name": "What should be kept in mind when preparing a food for child",
            "uuid": "5940388f-21a8-4d83-b2ec-376cd13a5197"
          },
          "displayOrder":8,
          "mandatory": true
        },
        {
          "name": "Other things that should be kept in mind while preparing food",
          "uuid": "ed21c064-2f81-4059-88b1-1caa076cbfc5",
          "keyValues": [],
          "concept": {
            "uuid": "c0b0e549-d209-4754-87bf-9b5f547a57d8",
            "name": "Other things that should be kept in mind while preparing food"
          },
          "displayOrder": 8.2,
          "mandatory": false
        },
        {
          "name": "What should be kept in mind while feed the child",
          "uuid": "29bfb199-00f0-4902-b587-3cbb63230722",
          "type": "MultiSelect",
          "keyValues": [],
          "concept": {
            "name": "What should be kept in mind while feed the child",
            "uuid": "27070a2b-1e0f-4d27-ab3a-1dd0280dcb44"
          },
          "displayOrder":9,
          "mandatory": true
        },
        {
          "name": "Other things that should be kept in mind while feed the child",
          "uuid": "59771259-cf11-4eda-9f05-03f6e9fdf3e3",
          "keyValues": [],
          "concept": {
            "uuid": "da907a63-1b50-4893-aa22-965a68ccabfe",
            "name": "Other things that should be kept in mind while feed the child"
          },
          "displayOrder":9.1 ,
          "mandatory": false
        }
      ]
    },
    {
      "uuid": "09c780a4-5346-4d2c-b2be-982ad10e5bfb",
      "name": "Information about practices followed by mother",
      "display": "Information about practices followed by mother",
      "displayOrder": 3,
      "formElements": [
        {
          "name": "What did you give to the child at birth",
          "uuid": "10207af8-052f-4cae-91ba-e4aab1edf865",
          "keyValues": [],
          "type": "SingleSelect",
          "concept": {
            "name": "What did you give to child at birth",
            "uuid": "a19b424b-33df-44aa-8f52-b24e3bf492a0"
          },
          "displayOrder": 1,
          "mandatory": true
        },
        {
          "name": "Till which age your child has breastfed exclusively",
          "uuid": "0bbb3a29-e331-4ca6-bbe9-9b603d24b1df",
          "keyValues": [],
          "type": "SingleSelect",
          "concept": {
            "name": "Till which age your child has breastfed exclusively",
            "uuid": "1cbb5491-2f4d-4e00-817a-8df6279557f2"

          },
          "displayOrder": 4,
          "mandatory": true
        },
        {
          "name": "When did you give water to the child",
          "uuid": "625c3492-4831-4da5-aa03-cc7299e0ced4",
          "keyValues": [],
          "type": "SingleSelect",
          "concept": {
            "name": "When did you give water to the child",
            "uuid": "a8d4d72a-3122-4d21-9c84-303fb9cb9916"
          },
          "displayOrder": 5,
          "mandatory": true
        },
        {
          "name": "When did you start giving complementary food to the child",
          "uuid": "d11683bb-7001-4350-828f-199a44f34b63",
          "keyValues": [],
          "type": "SingleSelect",
          "concept": {
            "name": "When did you start giving complementary food to the child",
            "uuid": "0b1e1783-428b-4428-8de1-4d32525c675a"
          },
          "displayOrder": 6,
          "mandatory": true
        },
        {
          "name": "Who has taken decision to start complementary food to the child",
          "uuid": "d24f2182-9e26-4f75-8ec9-92e003a1654e",
          "keyValues": [],
          "type": "SingleSelect",
          "concept": {
            "name": "Who has taken decision to start complementary food to the child",
            "uuid": "f13da8ee-65da-41a8-bf1c-d31672400a78"
          },
          "displayOrder": 7,
          "mandatory": true
        },
        {
          "name": "What type of food do you give to the child as complementary food",
          "uuid": "c1c0584a-36e0-428d-a757-e04c072dcf4c",
          "keyValues": [],
          "type": "MultiSelect",
          "concept": {
            "name": "What type of food do you give to the child as complementary food",
            "uuid": "045d4a3c-9b74-4e6f-96f8-da8f5a88547a"
          },
          "displayOrder": 8,
          "mandatory": true
        },
        {
          "name": "Other types of complementary food given to the child",
          "uuid": "e14e1c65-77ba-434e-bacf-d6c571db175f",
          "keyValues": [],
          "concept": {
            "uuid": "ac7fc74a-1b1e-43fe-a93f-39b175a59c2c",
            "name": "Other types of complementary food given to the child"
          },
          "displayOrder": 9,
          "mandatory": false
        },
        {
          "name": "How much do you give complementary food to the child",
          "uuid": "396cdcd8-5c6c-4882-9087-9b1e344708c4",
          "type":"MultiSelect",
          "keyValues": [],
          "concept": {
            "name": "How much do you give complementary food to the child",
            "uuid": "cd7c946f-3b75-4e74-8e9d-8f0218ea5d80"
          },
          "displayOrder": 10,
          "mandatory": true
        },
        {
          "name": "How often do you give complementary food to the children",
          "uuid": "e6e8127a-b94f-4990-85e3-cf45349f651b",
          "type":"MultiSelect",
          "keyValues": [],
          "concept": {
            "name": "How often do you give complementary food to the children",
            "uuid": "0e7e9ed1-9bc2-4258-855d-1d4cf477fe8d"
          },
          "displayOrder": 11,
          "mandatory": true
        },
        {
          "name": "What are the points you kept in a mind while preparing a food for the child",
          "uuid": "18e96e3f-cc31-4355-9184-0889660bec9f",
          "type":"MultiSelect",
          "keyValues": [],
          "concept": {
            "name": "What are the points you kept in a mind while preparing a food for the child",
            "uuid": "6d44f4c4-2b16-453b-a1ab-90eeee60a340"
          },
          "displayOrder":12,
          "mandatory": true
        },
        {
          "name": "Other points you kept in a mind while preparing a food for the child",
          "uuid": "2d76f718-230f-413b-8144-38039561ef63",
          "keyValues": [],
          "concept": {
            "uuid": "68437adf-35b1-4bad-b793-a9d4c6abf839",
            "name": "Other points you kept in a mind while preparing a food for the child"
            },
          "displayOrder": 13,
          "mandatory": false
        },
        {
          "name": "What are the points you kept in a mind while feed the child",
          "uuid": "22028277-a9bd-4b28-8a33-438b882532a6",
          "type":"MultiSelect",
          "keyValues": [],
          "concept": {
            "name": "What are the points you kept in a mind while feed the child",
            "uuid": "cf4376af-884d-4197-9b2a-9c43c4893aaa"
          },
          "displayOrder": 14,
          "mandatory": true
        },
        {
          "name": "Other points you kept in a mind while feed the child",
          "uuid": "2fa472bf-017a-40c9-98ee-2e5a41c6647c",
          "type":"SingleSelect",
          "keyValues": [],
          "concept": {
            "uuid": "00754cdd-7e55-49ae-a823-4cbe87399c13",
            "name": "Other points you kept in a mind while feed the child"
          },
          "displayOrder": 15,
          "mandatory": false
        },
        {
          "name": "Do you give complementary food along with breast feeding",
          "uuid": "52493fa0-25b9-4334-8287-8077cedf3863",
          "type":"SingleSelect",
          "keyValues": [],
          "concept": {
            "name": "Do you give complementary food along with breast feeding",
            "uuid": "df49722d-6ea2-405c-a109-7bcd2f6cf9db"
          },
          "displayOrder": 16,
          "mandatory": true
        },
        {
          "name": "When do you breastfeed to your child",
          "uuid": "9dc3de7f-16e8-4dca-9c33-f4ac6cfe69bc",
          "type":"SingleSelect",
          "keyValues": [],
          "concept": {
            "name": "When do you breastfeed to your child",
            "uuid": "aec3ddd6-b773-4e36-9ab1-9ed33d0eaaec"
          },
          "displayOrder": 17,
          "mandatory": true
        },
        {
          "name": "Why don't you give complementary food",
          "uuid": "d319cdaa-17f6-4020-b1bb-ddd761c055be",
          "keyValues": [],
          "concept": {
            "uuid": "441be07c-3453-4038-a7e0-8507ebfab549",
            "name": "Why don't you give complementary food"
          },
          "displayOrder": 18,
          "mandatory": true
        },
        {
          "name": "When do you wash child’s hand",
          "uuid": "dc04ab7f-116b-497c-be33-6e6d170e6400",
          "type":"MultiSelect",
          "keyValues": [],
          "concept": {
            "name": "When do you wash child’s hand",
             "uuid": "ff93d79e-299a-499b-a5af-2bc74a2267a7"
          },
          "displayOrder": 19,
          "mandatory": true
        }  
      ]
    },
    {
      "uuid": "cd710019-549b-4beb-8144-06d3a8dd5fd3",
      "name": "Services for lactating mother",
      "display": "Services for lactating mother",
      "displayOrder": 4,
      "formElements": [
        {
          "name": "Do you get snacks as take home ration from Anganwadi centre",
          "uuid": "851c8d52-cef9-4a3d-91cd-3469cc0ba67b",
          "type": "SingleSelect",
          "concept": {
            "name": "Do you get snacks as take home ration from Anganwadi centre",
            "uuid": "095d492c-92da-4194-a130-bb48a64a2c02"
          },
          "displayOrder": 1,
          "mandatory": true
        },
         {
          "name": "What does mother get as a snacks",
          "uuid": "d02dcec2-3c49-437f-8ded-f1a1790f3f89",
          "type":"MultiSelect",
          "keyValues": [],
          "concept": {
            "name": "What does mother get as a snacks",
            "uuid": "5fe0c780-042a-448f-b7d5-50c3a01a9fea"
          },
          "displayOrder":2.1,
          "mandatory": true
        },
        {
          "name": "How much quantity of Oil mother gets",
          "uuid": "b86da2fe-8493-49c8-b44a-f88fb2eb1afb",
          "keyValues": [],
          "concept": {
            "name": "How much quantity of Oil mother gets",
            "uuid": "8dcd7314-2ff9-4185-965f-311e989f6500"
          },
          "displayOrder":3.1,
          "mandatory": true
        },
        {
          "name": "How much quantity of Wheat mother gets",
          "uuid": "d6cdf2b2-c6d8-4c26-8035-0b4ea9d52a99",
          "keyValues": [],
          "concept": {
            "name": "How much quantity of Wheat mother gets",
            "uuid": "12ef4b24-859b-4de6-89fa-785c1c818c17"
          },
          "displayOrder":4.1,
          "mandatory": true
        },
        {
          "name": "How much quantity of Pulses mother gets",
          "uuid": "fb8fa119-f171-4e7a-934b-bd7fb9eb9b07",
          "keyValues": [],
          "concept": {
            "name": "How much quantity of Pulses mother gets",
            "uuid": "aec2dbaa-2947-4fff-9b99-130dc90a6fd7"
          },
          "displayOrder":5.1,
          "mandatory": true
        },
        {
          "name": "How much quantity of Salt mother gets",
          "uuid": "35e995ef-9586-4b9f-8083-c914a5aff2f9",
          "keyValues": [],
          "concept": {
            "name": "How much quantity of Salt mother gets",
            "uuid": "57b590fc-e84d-4345-954a-b7c162fe3c23"
          },
          "displayOrder":6.1,
          "mandatory": true
        },
        {
          "name": "What did you cook from the snacks received",
          "uuid": "2f9a26ae-0e8b-4994-8995-d40bdb35171e",
          "keyValues": [],
          "concept": {
            "uuid": "f75e6020-ce0a-46b9-ba53-13c2b31c4a23",
            "name": "What did you cook from the snacks received"
          },
          "displayOrder":7.1,
          "mandatory": true
        },
        {
          "name": "Got any benefits of government programme/scheme",
          "uuid": "00b89c03-61e6-4c50-817c-d30a57407aeb",
          "keyValues": [],
          "concept": {
            "name": "Got any benefits of government programme/scheme",
            "uuid": "defa9abf-0e40-4df8-b49a-c48ef52f6e0a"  
          },
          "displayOrder":8.1,
          "mandatory": true
        },
        {
          "name": "Programme/scheme under which received entitlements",
          "uuid": "ea5e91e8-c7e3-4a8f-8759-1581d05b914e",
          "keyValues": [],
          "concept": {
            "name": "Programme/scheme under which received entitlements",
            "uuid": "7cc5007f-ebc5-4b66-abd7-19231554422d"
          },
          "displayOrder":9.1,
          "mandatory": true
        },
        {
          "name": "Reason for not getting benefits under government programme/scheme",
          "uuid": "c2c40bc4-28a8-4aab-87a6-5df069f805e9",
          "keyValues": [],
          "concept": {
            "name": "Reason for not getting benefits under government programme/scheme",
            "uuid": "e4ebdc27-6d52-47ce-86ad-4f9c63609c51"
          },
          "displayOrder":10.1,
          "mandatory": true
        },
        {
          "name": "Other reason for not getting benefits",
          "uuid": "a69aa67e-eb0d-49e0-ae1a-0f6eb09f77aa",
          "keyValues": [],
          "concept": {
            "uuid": "48717220-15b0-4c61-9186-3f5ccec69246",
            "name": "Other reason for not getting benefits"
            
          },
          "displayOrder":11.1,
          "mandatory":false
        }     
      ]
    },
    {
      "uuid": "d2d99f6d-a136-409c-922e-7735873ac61c",
      "name": "Information about uses of contraception",
      "display": "Information about uses of contraception",
      "displayOrder": 5,
      "formElements": [
        {
          "name": "Did you use any method of contraception before pregnancy",
          "uuid": "864659ba-504f-4517-88e1-69f61d1f06ba",
          "type": "SingleSelect",
          "concept": {
            "name": "Did you use any method of contraception before pregnancy",
            "uuid": "b27c26df-c639-4596-97e7-91ab818b7bff"
          },
          "displayOrder": 1,
          "mandatory": true
        },
        {
          "name": "Method of contraception used",
          "uuid": "2460d2c9-a939-4cbc-946b-fceb2745edce",
          "keyValues": [],
          "type": "MultiSelect",
          "concept": {
            "name": "Method of contraception used",
            "uuid": "7491c731-9292-4d66-9c00-1b7fe6c2e02f"
          },
          "displayOrder": 2,
          "mandatory": true
        },
        {
          "name": "From where/whom information about contraception received",
          "uuid": "416bd0e6-be3a-4b4f-a36a-517db40d67d0",
          "keyValues": [],
          "type": "MultiSelect",
          "concept": {
            "name": "From where/whom information about contraception received",
            "uuid": "18ad6262-1688-48d4-a584-84958ebdeb0c"
          },
          "displayOrder": 3,
          "mandatory": true
        },
        {
          "name": "Other source from where/whom information about contraception received",
          "uuid": "60e1c68d-6559-47a9-81e5-b87f637b68ea",
          "keyValues": [],
          "concept": {
            "uuid": "5cbcfde1-db48-4f24-a66d-c7416ec3237a",
            "name": "Other source from where/whom information about contraception received"
          },
          "displayOrder": 4,
          "mandatory": true
        }
      ]
    },
    {
      "uuid": "2b6f8233-b708-4a8c-a57e-f0acdf02372d",
      "name": "Information about addiction",
      "display": "Information about addiction",
      "displayOrder": 6,
      "formElements": [
        {
          "name": "Do you have any addiction",
          "uuid": "c6925c72-f0db-4dce-a9d6-01f106238989",
          "type": "SingleSelect",
          "concept": {
            "name": "Do you have any addiction",
            "uuid": "4f541cf6-629f-49ae-a1fd-609b04d8ce23"
          },
          "displayOrder": 1,
          "mandatory": true
        },
        {
          "name": "What do you consume",
          "uuid": "f5a9a9db-be8e-45eb-ba9d-f99d0b9f633f",
          "keyValues": [],
          "type": "MultiSelect",
          "concept": {
            "name": "What do you consume",
            "uuid": "b0607fe4-6c72-47c5-9661-e44d6560fb1b"
          },
          "displayOrder": 2,
          "mandatory": true
        }
      ]
    }
  ]
}